MiniToolkit/__init__.py
MiniToolkit/convert/__init__.py
MiniToolkit/convert/caculate_instances.py
MiniToolkit/convert/labelme2coco.py
MiniToolkit/tools/__init__.py
MiniToolkit/tools/bar.py
MiniToolkit/tools/image.py
MiniToolkit/tools/label.py
MiniToolkit/tools/mask.py
MiniToolkit/tools/metric.py
MiniToolkit/tools/path.py
minitoolkit-0.1.4.dist-info/licenses/LICENSE
minitoolkit-0.1.4.dist-info/METADATA
minitoolkit-0.1.4.dist-info/WHEEL
minitoolkit-0.1.4.dist-info/top_level.txt
minitoolkit-0.1.4.dist-info/RECORD
