Metadata-Version: 2.4
Name: MiniToolkit
Version: 0.1.4
Summary: 常用功能模块快速使用库.
Classifier: Programming Language :: Python :: 3
Classifier: License :: OSI Approved :: Apache Software License
Requires-Python: >=3.10
License-File: LICENSE
Requires-Dist: pillow>=8.1.0
Requires-Dist: opencv-python>=4.3.0.38
Dynamic: license-file
